anytext/__init__.py
anytext/aiy.py
anytext/bert_tokenizer.py
anytext/dataset_util.py
anytext/t3_dataset.py
anytext/util.py
anytext/cldm/__init__.py
anytext/cldm/cldm.py
anytext/cldm/ddim_hacked.py
anytext/cldm/embedding_manager.py
anytext/cldm/hack.py
anytext/cldm/logger.py
anytext/cldm/model.py
anytext/cldm/recognizer.py
anytext/font/Arial_Unicode.ttf
anytext/ldm/__init__.py
anytext/ldm/util.py
anytext/ldm/data/__init__.py
anytext/ldm/data/util.py
anytext/ldm/models/__init__.py
anytext/ldm/models/autoencoder.py
anytext/ldm/models/diffusion/__init__.py
anytext/ldm/models/diffusion/ddim.py
anytext/ldm/models/diffusion/ddpm.py
anytext/ldm/models/diffusion/plms.py
anytext/ldm/models/diffusion/sampling_util.py
anytext/ldm/models/diffusion/dpm_solver/__init__.py
anytext/ldm/models/diffusion/dpm_solver/dpm_solver.py
anytext/ldm/models/diffusion/dpm_solver/sampler.py
anytext/ldm/modules/__init__.py
anytext/ldm/modules/attention.py
anytext/ldm/modules/ema.py
anytext/ldm/modules/diffusionmodules/__init__.py
anytext/ldm/modules/diffusionmodules/model.py
anytext/ldm/modules/diffusionmodules/openaimodel.py
anytext/ldm/modules/diffusionmodules/upscaling.py
anytext/ldm/modules/diffusionmodules/util.py
anytext/ldm/modules/distributions/__init__.py
anytext/ldm/modules/distributions/distributions.py
anytext/ldm/modules/encoders/__init__.py
anytext/ldm/modules/encoders/modules.py
anytext/ldm/modules/image_degradation/__init__.py
anytext/ldm/modules/image_degradation/bsrgan.py
anytext/ldm/modules/image_degradation/bsrgan_light.py
anytext/ldm/modules/image_degradation/utils_image.py
anytext/ldm/modules/midas/__init__.py
anytext/ldm/modules/midas/api.py
anytext/ldm/modules/midas/utils.py
anytext/ldm/modules/midas/midas/__init__.py
anytext/ldm/modules/midas/midas/base_model.py
anytext/ldm/modules/midas/midas/blocks.py
anytext/ldm/modules/midas/midas/dpt_depth.py
anytext/ldm/modules/midas/midas/midas_net.py
anytext/ldm/modules/midas/midas/midas_net_custom.py
anytext_z-0.1.2.dist-info/LICENSE
anytext_z-0.1.2.dist-info/METADATA
anytext_z-0.1.2.dist-info/WHEEL
anytext_z-0.1.2.dist-info/top_level.txt
anytext_z-0.1.2.dist-info/RECORD
