Metadata-Version: 2.1
Name: anytext-z
Version: 0.1.2
Summary: AnyText
License-File: LICENSE
Requires-Dist: pytorch-lightning (>=1.5.0)
Requires-Dist: jieba (==0.42.1)
Requires-Dist: subword-nmt (==0.3.8)
Requires-Dist: sacremoses (==0.0.53)
